diogo_caribe_first_package/__init__.py
diogo_caribe_first_package/module1_name/__init__.py
diogo_caribe_first_package/module1_name/file1_name.py
diogo_caribe_first_package/module1_name/file2_name.py
diogo_caribe_first_package/module2_name/__init__.py
diogo_caribe_first_package/module2_name/file1_name.py
diogo_caribe_first_package/module2_name/file2_name.py
diogo_caribe_first_package-0.1.0.dist-info/METADATA
diogo_caribe_first_package-0.1.0.dist-info/WHEEL
diogo_caribe_first_package-0.1.0.dist-info/RECORD
